a2p2/__init__.py
a2p2/__main__.py
a2p2/client.py
a2p2/facility.py
a2p2/gui.py
a2p2/instrument.py
a2p2/ob.py
a2p2/samp.py
a2p2/utils.py
a2p2/version.py
a2p2/chara/__init__.py
a2p2/chara/facility.py
a2p2/chara/gui.py
a2p2/jmmc/__init__.py
a2p2/jmmc/catalogs.py
a2p2/jmmc/generated_models.py
a2p2/jmmc/models.py
a2p2/jmmc/services.py
a2p2/jmmc/utils.py
a2p2/jmmc/webservices.py
a2p2/vlti/__init__.py
a2p2/vlti/facility.py
a2p2/vlti/gravity.py
a2p2/vlti/gui.py
a2p2/vlti/instrument.py
a2p2/vlti/matisse.py
a2p2/vlti/pionier.py
a2p2/vlti/conf/GRAVITY_ditTable.json
a2p2/vlti/conf/GRAVITY_rangeTable.json
a2p2/vlti/conf/MATISSE_ditTable.json
a2p2/vlti/conf/MATISSE_rangeTable.json
a2p2/vlti/conf/PIONIER_ditTable.json
a2p2/vlti/conf/PIONIER_rangeTable.json
a2p2-0.7.9.dist-info/licenses/LICENSE
a2p2-0.7.9.dist-info/METADATA
a2p2-0.7.9.dist-info/WHEEL
a2p2-0.7.9.dist-info/entry_points.txt
a2p2-0.7.9.dist-info/top_level.txt
a2p2-0.7.9.dist-info/RECORD
