Metadata-Version: 2.4
Name: a2p2
Version: 0.7.9
Author-email: JMMC Tech Group <jmmc-tech-group@jmmc.fr>
License: OSI Approved :: GNU General Public License v3 (GPLv3)
Project-URL: Homepage, https://www.jmmc.fr/a2p2
Project-URL: Bug Reports, https://github.com/JMMC-OpenDev/a2p2/issues
Project-URL: Source, https://github.com/JMMC-OpenDev/a2p2
Keywords: observation,optical-interferometry,p2,preparation,samp,tool
Classifier: Development Status :: 4 - Beta
Classifier: Intended Audience :: Developers
Classifier: Programming Language :: Python :: 3
Classifier: Programming Language :: Python :: 3.6
Requires-Python: >=3
License-File: LICENSE
Requires-Dist: appdirs
Requires-Dist: astropy>=5.2.2
Requires-Dist: pyvo>=1.6.1
Requires-Dist: p2api
Dynamic: license-file
